jhub_remote_login/__init__.py
jhub_remote_login/_dummy_auth.py
jhub_remote_login/_jhub_remote_auth.py
jhub_remote_login-0.2.119.dist-info/METADATA
jhub_remote_login-0.2.119.dist-info/RECORD
jhub_remote_login-0.2.119.dist-info/WHEEL
jhub_remote_login-0.2.119.dist-info/top_level.txt
