Metadata-Version: 2.1
Name: jhub-remote-login
Version: 0.2.119
Summary: REMOTE_USER Authenticator: An Authenticator for Jupyterhub to read user information from HTTP request headers, as when running behind an authenticating proxy. Based on https://github.com/cwaldbieser/jhub_remote_user_authenticator and https://github.com/rasmunk/jhub-authenticators
Home-page: https://github.com/cbjuan/jhub_remote_login
Author: Juan Cruz-Benito
Author-email: juan.cruz@ibm.com
License: GPLv3
Keywords: Interactive,Interpreter,Shell,Web
Platform: Linux
Platform: Mac OS X
Classifier: Intended Audience :: Developers
Classifier: Intended Audience :: System Administrators
Classifier: Intended Audience :: Science/Research
Classifier: License :: OSI Approved :: GNU General Public License v3 (GPLv3)
Classifier: Programming Language :: Python
Classifier: Programming Language :: Python :: 3
Requires-Dist: jupyterhub
